mypackage/__init__.py
mypackage/__version__.py
mypackage/core.py
LTK_cicy-0.1.0.dist-info/LICENSE
LTK_cicy-0.1.0.dist-info/METADATA
LTK_cicy-0.1.0.dist-info/WHEEL
LTK_cicy-0.1.0.dist-info/top_level.txt
LTK_cicy-0.1.0.dist-info/RECORD
