Metadata-Version: 2.1
Name: LTK-cicy
Version: 0.1.0
Summary: Linked Reads Tool Kit
Home-page: https://github.com/CicyYeung/VFDetector
Author: YANG CHAO
Author-email: yangchaogab@gmail.com
License: MIT
Platform: UNKNOWN
Classifier: License :: OSI Approved :: MIT License
Classifier: Programming Language :: Python
Classifier: Programming Language :: Python :: 3
Classifier: Programming Language :: Python :: 3.6
Classifier: Programming Language :: Python :: Implementation :: CPython
Classifier: Programming Language :: Python :: Implementation :: PyPy
Requires-Python: >=3.6.0
